segmentation_dxf/__init__.py
segmentation_dxf/__main__.py
segmentation_dxf/convert.py
segmentation_dxf/convert_buffer.py
segmentation_dxf/convert_filename.py
segmentation_dxf/test_convert.py
segmentation_dxf-0.3.0.dist-info/LICENSE
segmentation_dxf-0.3.0.dist-info/WHEEL
segmentation_dxf-0.3.0.dist-info/METADATA
segmentation_dxf-0.3.0.dist-info/RECORD
