Metadata-Version: 2.1
Name: segmentation-dxf
Version: 0.3.0
Summary: 
Author: elisaAiwizo
Author-email: elisa@aiwizo.com
Requires-Python: >=3.7,<4.0
Classifier: Programming Language :: Python :: 3
Classifier: Programming Language :: Python :: 3.7
Classifier: Programming Language :: Python :: 3.8
Classifier: Programming Language :: Python :: 3.9
Requires-Dist: Pillow (>=8.0.1,<9.0.0)
Requires-Dist: ezdxf (>=0.14.2,<0.15.0)
Requires-Dist: matplotlib (>=3.3.3,<4.0.0)
Requires-Dist: more-itertools (>=8.6.0,<9.0.0)
Requires-Dist: numpy (>=1.19.4,<2.0.0)
Requires-Dist: opencv-python (>=4.4.0,<5.0.0)
